{"file_name": "U_10_1", "number_of_trucks": 2, "drone_capacity": 2, "number_of_drones": 2, "iteration": 1, "best_fitness": 239.72643680968147, "runtime": 16.990278482437134, "best_solution": [[[[0, [6]], [6, []], [2, [2, 4]], [1, [1, 10]], [10, []], [4, []]], [[0, [8, 3]], [8, []], [3, []], [7, [7, 5]], [5, []], [9, [9]]]], [[[2, [2, 4]]], [[1, [1, 10]]], [[7, [7, 5]]], [[9, [9]]]]]}
{"file_name": "U_10_1", "number_of_trucks": 2, "drone_capacity": 2, "number_of_drones": 2, "iteration": 2, "best_fitness": 238.0018579854045, "runtime": 18.47120237350464, "best_solution": [[[[0, [6]], [6, []], [10, [10, 1]], [1, []]], [[0, []], [8, [8, 3, 2]], [2, []], [3, []], [5, [5, 7]], [7, []], [9, [9, 4]], [4, []]]], [[[8, [3, 2]]], [[8, [8]]], [[10, [10, 1]]], [[5, [5, 7]]], [[9, [9, 4]]]]]}
{"file_name": "U_10_1", "number_of_trucks": 2, "drone_capacity": 2, "number_of_drones": 2, "iteration": 3, "best_fitness": 239.72643680968147, "runtime": 16.296947240829468, "best_solution": [[[[0, [8, 3]], [8, []], [3, []], [7, [7, 5]], [5, []], [9, [9]]], [[0, []], [2, [2, 4, 6]], [1, [1, 10]], [6, []], [10, []], [4, []]]], [[[2, [6]]], [[2, [2, 4]]], [[1, [1, 10]]], [[7, [7, 5]]], [[9, [9]]]]]}
