{"file_name": "U_10_0", "number_of_trucks": 2, "drone_capacity": 2, "number_of_drones": 2, "iteration": 1, "best_fitness": 188.49395374481617, "runtime": 11.639532089233398, "best_solution": [[[[0, []], [9, [9]], [7, [7, 5]], [5, []], [1, [1, 3]], [3, []]], [[0, []], [8, [8]], [2, [2, 6]], [6, []], [4, [4, 10]], [10, []]]], [[[9, [9]]], [[8, [8]]], [[2, [2, 6]]], [[7, [7, 5]]], [[1, [1, 3]]], [[4, [4, 10]]]]]}
{"file_name": "U_10_0", "number_of_trucks": 2, "drone_capacity": 2, "number_of_drones": 2, "iteration": 2, "best_fitness": 184.02199888796545, "runtime": 9.628694772720337, "best_solution": [[[[0, [9]], [9, []], [2, [2, 6]], [6, []], [4, [4, 10]], [10, []]], [[0, []], [3, [3, 8]], [5, [5]], [8, []], [1, [1, 7]], [7, []]]], [[[3, [3, 8]]], [[5, [5]]], [[2, [2, 6]]], [[1, [1, 7]]], [[4, [4, 10]]]]]}
{"file_name": "U_10_0", "number_of_trucks": 2, "drone_capacity": 2, "number_of_drones": 2, "iteration": 3, "best_fitness": 187.1970944188425, "runtime": 11.904924869537354, "best_solution": [[[[0, []], [4, [4, 9]], [6, [6, 2]], [2, []], [10, [10]], [9, []]], [[0, []], [3, [3, 8]], [8, []], [1, [1, 5]], [5, []], [7, [7]]]], [[[3, [3, 8]]], [[4, [4, 9]]], [[6, [6, 2]]], [[1, [1, 5]]], [[10, [10]]], [[7, [7]]]]]}
